underautomation/__init__.py
underautomation/yaskawa/__init__.py
underautomation/yaskawa/connect_parameters.py
underautomation/yaskawa/yaskawa_robot.py
underautomation/yaskawa/common/__init__.py
underautomation/yaskawa/common/high_speed_e_server_connect_parameters.py
underautomation/yaskawa/high_speed_e_server/__init__.py
underautomation/yaskawa/high_speed_e_server/alarm_reset_type.py
underautomation/yaskawa/high_speed_e_server/arm_flip_information.py
underautomation/yaskawa/high_speed_e_server/axis_flip_information.py
underautomation/yaskawa/high_speed_e_server/control_group.py
underautomation/yaskawa/high_speed_e_server/flip_no_flip_information.py
underautomation/yaskawa/high_speed_e_server/get_file_progress.py
underautomation/yaskawa/high_speed_e_server/high_speed_e_server_client.py
underautomation/yaskawa/high_speed_e_server/invalid_data_answer_exception.py
underautomation/yaskawa/high_speed_e_server/load_file_progress.py
underautomation/yaskawa/high_speed_e_server/management_time_type.py
underautomation/yaskawa/high_speed_e_server/on_off_command_type.py
underautomation/yaskawa/high_speed_e_server/orientation_flip_information.py
underautomation/yaskawa/high_speed_e_server/position_command_classification.py
underautomation/yaskawa/high_speed_e_server/position_command_operation_coordinate.py
underautomation/yaskawa/high_speed_e_server/position_command_type.py
underautomation/yaskawa/high_speed_e_server/regarded_reverse_position_specified.py
underautomation/yaskawa/high_speed_e_server/robot_alarm_data.py
underautomation/yaskawa/high_speed_e_server/robot_alarm_data_extended.py
underautomation/yaskawa/high_speed_e_server/robot_axis_raw_data_1.py
underautomation/yaskawa/high_speed_e_server/robot_base_position_data.py
underautomation/yaskawa/high_speed_e_server/robot_base_position_type.py
underautomation/yaskawa/high_speed_e_server/robot_control_group.py
underautomation/yaskawa/high_speed_e_server/robot_data.py
underautomation_yaskawa-1.3.0.0.dist-info/METADATA
underautomation_yaskawa-1.3.0.0.dist-info/WHEEL
underautomation_yaskawa-1.3.0.0.dist-info/top_level.txt
underautomation_yaskawa-1.3.0.0.dist-info/RECORD
