Metadata-Version: 2.4
Name: UnderAutomation.Yaskawa
Version: 1.3.0.0
Summary: Quickly create applications that communicate with your Yaskawa robots
Home-page: https://underautomation.com/yaskawa
Author: UnderAutomation
Author-email: support@underautomation.com
Project-URL: Documentation, https://underautomation.com/yaskawa/documentation/get-started-python
Project-URL: Source, https://github.com/underautomation/Yaskawa.py
Requires-Python: >=3.7
Requires-Dist: pythonnet==3.0.5
Dynamic: author
Dynamic: author-email
Dynamic: description
Dynamic: description-content-type
Dynamic: home-page
Dynamic: project-url
Dynamic: requires-dist
Dynamic: requires-python
Dynamic: summary
